toscawidgets
