Metadata-Version: 1.0
Name: twPrototype
Version: 1.5dev-r792
Summary: Wrapper for the Prototype Javascript Library for ToscaWidgets
Home-page: UNKNOWN
Author: Claudio Martinez
Author-email: claudio.s.martinez@gmail.com
License: UNKNOWN
Keywords: toscawidgets.widgets
Platform: UNKNOWN
